{
  "last_run": "2026-05-11T06:28:00-04:00",
  "last_run_result": "outreach_drafted_4_orgs",
  "orgs_due_today": 4,
  "orgs_queued_may_11": 0,
  "orgs_queued_may_12": 7,
  "query_idx": 8,
  "google_places_prospecting_daily": true,
  "notes": "Cron ran at 6:28 AM EDT Monday. Drafted 4 follow-ups: KLR (followup-2), Storm Shield (followup-2), Atlantic Water (followup-1), SafeHaven (followup-2). Next touches: May 12 (7 orgs initial+followup-1). LinkedIn sequences from May 4 pending review.",
  "seen": [
    "BUCKEYE PLUMBING INC",
    "FLORIDA PROPERTY MANAGEMENT SERVICES LLC",
    "DAMAGE SERVICES- MOLD REMEDIATION & SMOKE CLEANUP",
    "PAUL DAVIS RESTORATION OF PALM BEACH COUNTY",
    "PREMIER ROOFER WEST PALM BEACH",
    "CEE DEE AIR CONDITIONING, INC",
    "SOUTH FLORIDA ROOFING",
    "COUNTRYSIDE LOXAHATCHEE HVAC REPAIR",
    "KIMSTO CONSTRUCTION LLC",
    "FLORIDA COAST CONTRACTING & ROOFING",
    "ISLAND CONSTRUCTION & DESIGN",
    "COMPLETE ROOFING SOLUTIONS INC.",
    "SUPERCLEAN RESTORATION OF THE PALM BEACHES LLC",
    "LEADING PLUMBING SERVICES LLC",
    "MIKE THE PLUMBER INC",
    "TOP ROOFER WEST PALM BEACH",
    "SHORELINE AIR CONDITIONING",
    "ELITE ROOFING INC",
    "TRICOLI TEAM-KELLER WILLIAMS REALTY",
    "MANGROVE PROPERTY MANAGEMENT & SALES",
    "HOME SALES AND PROPERTY MANAGEMENT",
    "PALM BEACH PROPERTY MANAGEMENT",
    "PALM BEACH COUNTY PROPERTY MANAGEMENT",
    "ALL STAR PLUMBING & AIR",
    "ATLANTIC VIEW BUILDERS & REMODELING",
    "HOME PROPERTY MANAGEMENT",
    "EWING & EWING AIR CONDITIONING",
    "DAVENPORT PROFESSIONAL PROPERTY MANAGEMENT",
    "RAINBOW ROOFING LLC",
    "EVANS ROOFING OF THE PALM BEACHES",
    "RENOVA - RENOVATION & REMODELING GENERAL CONTRACTORS",
    "FERNANDEZ PLUMBING LLC",
    "ATLIS PROPERTY MANAGEMENT",
    "SERAC CONSTRUCTION INC",
    "REMEDIATION 911",
    "ELITE CONTRACTORS PRO-GENERAL CONSTRUCTION & REMODELING COMPANY-HOME IMPROVEMENT COMPANY",
    "RAPID WATER DAMAGE RESTORATION WELLINGTON FL",
    "FLAMINGO PLUMBING & BACKFLOW",
    "LINDSTROM AIR CONDITIONING & PLUMBING",
    "KYZAR AIR CONDITIONING",
    "STEVE CURY CONSTRUCTION",
    "COASTAL RESTORATION SPECIALISTS",
    "A.R. WILLIAMS AIR CONDITIONING",
    "SWIFT AIR CONDITIONING",
    "ALTEC ROOFING",
    "RYAN JENNINGS GROUP | KELLER WILLIAMS REALTY",
    "MATOS CONTRACTING INC",
    "WEST PALM CONTRACTING",
    "ORCHID PROPERTY MANAGEMENT",
    "HVAC AND PLUMBING WEST PALM BEACH | PREMIER COMFORT SERVICES, INC.",
    "ALL COUNTY ELITE PROPERTY MANAGEMENT",
    "REAL PROPERTY MANAGEMENT SUNSTATE",
    "GULFSTREAM COOLING",
    "ORCHID CITY RESTORATION",
    "HILLING AIR CONDITIONING INC",
    "COPPERHEAD PLUMBING LLC",
    "CLS ROOFING",
    "WATER CLEANUP OF FLORIDA",
    "SUPERIOR ROOFING OF FLORIDA, INC.",
    "MOLD AND WATER FLORIDA",
    "FIRST DEGREE AIR CONDITIONING, INC.",
    "ONE HOUR AIR CONDITIONING & HEATING OF WEST PALM BEACH",
    "A & H SERVICES, INC.",
    "HG PROPERTY MANAGEMENT",
    "AIRWORX AIR CONDITIONING & REFRIGERATION, INC.",
    "OAK CONSTRUCTION LLC",
    "MAYFAIR PROPERTY MANAGEMENT OF PALM BEACH COUNTY",
    "THE PHOENIX RESTORATION WATER DAMAGE, MOLD REMEDIATION, EMERGENCY WATER REPAIR IN LAKE WORTH",
    "THUNDER RESTORATION",
    "SANSONE AIR CONDITIONING, PLUMBING, & ELECTRICAL",
    "ACE PRO ROOFING",
    "RESCUE CLEAN 911 WATER DAMAGE, MOLD REMEDIATION, AIR DUCT CLEANING IN WELLINGTON",
    "NIK'S ROOFING LLC",
    "TPG PROPERTY MANAGEMENT",
    "BELMONTE BUILDING COMPANY",
    "PALM BEACH INTERNATIONAL REALTY",
    "MH MANAGEMENT SOLUTIONS CORP",
    "COASTAL ROOFING OF SOUTH FLORIDA",
    "HOUSE CALL CONSTRUCTION - REMODELING CUSTOM KITCHENS AND BATHS",
    "CHEERFUL AGENTS REAL ESTATE LLC.",
    "MY AREA REALTY WEST PALM BEACH PROPERTY MANAGEMENT",
    "PREFERRED AIR CONDITIONING & MECHANICAL, LLC",
    "KLR ROOFING CORP.",
    "ROOFER WEST PALM BEACH",
    "ROOFING SYSTEMS OF FLORIDA, INC",
    "NEAL ROOFING & WATERPROOFING",
    "KANGA PROPERTY MANAGEMENT",
    "KEYRENTER PROPERTY MANAGEMENT SOUTH FLORIDA",
    "WEST PALM BEACH WATER DAMAGE",
    "ADU WATER FIRE MOLD STORM",
    "RESCUE CLEAN 911 WATER DAMAGE, MOLD REMEDIATION, AIR DUCT CLEANING IN WEST PALM BEACH",
    "A1 PRO ROOFING, LLC",
    "CIRCLE HOMES \u2b55\ufe0f",
    "CHAIMAE YAAGOUBI, PA | REAL ESTATE AGENCY | PALM BEACH FLORIDA",
    "PALM BEACH RESIDENTIAL REMODELING",
    "STANLEY RESTORATION SERVICES",
    "ASSOCIATED PROPERTY MANAGEMENT OF THE PALM BEACHES INC.",
    "TITAN RESTORATION CONSTRUCTION",
    "HOPKINS AIR CONDITIONING",
    "WILDER REAL ESTATE GROUP",
    "NCCS CONSTRUCTION LLC",
    "SHIELD WATER DAMAGE RESTORATION WEST PALM BEACH FL",
    "CAMPBELL PROPERTY MANAGEMENT - LAKE WORTH",
    "PRO-TECH CORP",
    "DONOHUE REAL ESTATE",
    "LEON ROOFING CONTRACTOR"
  ]
}